LICENSE
MANIFEST.in
README.rst
setup.py
created_cards/delete-card.png
created_cards/hitler-card.png
created_cards/jail-card.png
created_cards/leave-card.png
created_cards/passed-card.png
created_cards/tombstone-card.png
created_cards/trash-card.png
created_cards/wanted-card.png
created_cards/welcome-card.png
maxi_card.py.egg-info/PKG-INFO
maxi_card.py.egg-info/SOURCES.txt
maxi_card.py.egg-info/dependency_links.txt
maxi_card.py.egg-info/requires.txt
maxi_card.py.egg-info/top_level.txt
maxicard/__init__.py
maxicard/fonts/SFMono.ttf
maxicard/imgs/delete-bg.png
maxicard/imgs/hitler-bg.png
maxicard/imgs/jail-bg.png
maxicard/imgs/passed-bg.png
maxicard/imgs/tombstone-bg.png
maxicard/imgs/trash-bg.png
maxicard/imgs/wanted-bg.png