Metadata-Version: 2.1
Name: maxi-card.py
Version: 1.0.4
Summary: This is simple maker for cards welcome and leave in discord bot.
Home-page: 
Author: Maxi_TM
Author-email: maksymilianratajczak794@gmail.com
License: MIT
Keywords: discord welcome card
Classifier: Development Status :: 5 - Production/Stable
Classifier: Intended Audience :: Education
Classifier: Operating System :: Microsoft :: Windows :: Windows 10
Classifier: License :: OSI Approved :: MIT License
Classifier: Programming Language :: Python :: 3
License-File: LICENSE
